lektor_minification.py
lektor_minification-1.1.5.dist-info/DESCRIPTION.rst
lektor_minification-1.1.5.dist-info/METADATA
lektor_minification-1.1.5.dist-info/RECORD
lektor_minification-1.1.5.dist-info/WHEEL
lektor_minification-1.1.5.dist-info/entry_points.txt
lektor_minification-1.1.5.dist-info/metadata.json
lektor_minification-1.1.5.dist-info/top_level.txt
