Metadata-Version: 2.0
Name: lektor-minification
Version: 1.1.5
Summary: A simple Lektor plugin to minify images at build time.
Home-page: https://github.com/numericube/lektor-minification
Author: Pierre-Julien Grizel
Author-email: pjgrizel@numericube.com
License: GNU GPLv3
Platform: any
Classifier: Development Status :: 4 - Beta
Classifier: Environment :: Web Environment
Classifier: Intended Audience :: Developers
Classifier: License :: OSI Approved :: GNU General Public License v3 (GPLv3)
Classifier: Operating System :: OS Independent
Classifier: Programming Language :: Python :: 2.7
Classifier: Topic :: Internet :: WWW/HTTP :: Site Management
Classifier: Topic :: Software Development :: Libraries :: Python Modules
Requires-Dist: Lektor
Requires-Dist: Pillow
Requires-Dist: pyimagediet
